{
    "instances": {
        "g3s.xlarge": {
            "provider": "ec2",
            "prices": {
                "on-demand": 0.75,
                "preemptible": 0.225
            },
            "restrictions": {
                "limits": {
                    "on-demand": 999999999,
                    "preemptible": 999999999
                },
                "markets": {
                    "on-demand": "yes",
                    "preemptible": "yes"
                }
            },
            "image_id": "ami-080af420cdfb56e39",
            "ebs_device_name": "/dev/xvdf",
            "vcpu": 0,
            "memory": 0,
            "gpu": "yes"
        },
        "n2-standard-2": {
            "provider": "gcloud",
            "prices": {
                "on-demand": 0.09711800000000001,
                "preemptible": 0.023498
            },
            "restrictions": {
                "limits": {
                    "on-demand": 999999999,
                    "preemptible": 999999999
                },
                "markets": {
                    "on-demand": "yes",
                    "preemptible": "yes"
                }
            },
            "image_id": "disk-ubuntu-flower-server",
            "ebs_device_name": "/dev/sdb",
            "memory": 8,
            "vcpu": 2,
            "gpu": "no"
        }
    }
}